str2d/__init__.py
Str2D-0.2.6.dist-info/LICENSE.txt
Str2D-0.2.6.dist-info/METADATA
Str2D-0.2.6.dist-info/WHEEL
Str2D-0.2.6.dist-info/top_level.txt
Str2D-0.2.6.dist-info/RECORD
